pythonseer/__init__.py
pythonseer/censure.py
pythonseer/endorsement.py
pythonseer/fediseer.py
pythonseer/guarantee.py
pythonseer/hesitation.py
pythonseer/requestor.py
pythonseer/suspicions.py
pythonseer/types/__init__.py
pythonseer/types/format.py
pythonseer/whitelist.py
pythonseer-0.3.5.dist-info/LICENSE
pythonseer-0.3.5.dist-info/METADATA
pythonseer-0.3.5.dist-info/WHEEL
pythonseer-0.3.5.dist-info/RECORD
